<?xml version="1.0" encoding="UTF-8"?>
<site>
   <description>
      Mylyn Docs EPUB
   </description>
   <feature url="features/org.eclipse.mylyn.docs.epub_0.0.0.jar" id="org.eclipse.mylyn.docs.epub" version="0.0.0">
      <category name="Features"/>
   </feature>
   <feature url="features/org.eclipse.mylyn.docs.epub.sdk_0.0.0.jar" id="org.eclipse.mylyn.docs.epub.sdk" version="0.0.0">
      <category name="SDK"/>
   </feature>
   <category-def name="Features" label="Mylyn Docs EPUB Features">
      <description>
         Tools.
      </description>
   </category-def>
   <category-def name="SDK" label="Mylyn Docs EPUB SDK and Framework">
      <description>
         Source code and documentation for integrators.
      </description>
   </category-def>
</site>
